mockallan/__init__.py
mockallan/__main__.py
mockallan/app_handler.py
mockallan/history.py
mockallan/main.py
mockallan/request.py
mockallan/stub_config.py
mockallan/validators.py
mockallan-0.1.1.dist-info/LICENSE
mockallan-0.1.1.dist-info/METADATA
mockallan-0.1.1.dist-info/WHEEL
mockallan-0.1.1.dist-info/entry_points.txt
mockallan-0.1.1.dist-info/top_level.txt
mockallan-0.1.1.dist-info/RECORD
