Metadata-Version: 2.1
Name: mockallan
Version: 0.1.1
Summary: Lightweight HTTP server mock for CI and testing environments.
Home-page: https://github.com/david-domz/mockallan
Author: David Domínguez
Author-email: david.7b8@gmail.com
License: MIT
Keywords: python,http,REST,mock,test,pytest
Platform: UNKNOWN
Classifier: Development Status :: 4 - Beta
Classifier: Environment :: Console
Classifier: Intended Audience :: Developers
Classifier: License :: OSI Approved :: MIT License
Classifier: Programming Language :: Python :: 3.10
Classifier: Programming Language :: Python :: 3.11
Classifier: Topic :: Software Development :: Testing
Classifier: Topic :: Software Development :: Testing :: Mocking
Classifier: Topic :: Internet :: WWW/HTTP
Classifier: Topic :: Software Development :: Libraries :: Python Modules
Classifier: Operating System :: OS Independent
Requires-Python: >=3.8, <4
Requires-Dist: jsonschema<4.0.0,>=3.0.0
Requires-Dist: lxml<5.0.0,>=4.0.0
Provides-Extra: dev
Requires-Dist: coverage>=6.0; extra == "dev"
Requires-Dist: pytest>=7.4.2; extra == "dev"
Requires-Dist: twine>=4.0.2; extra == "dev"
